aliyunsdkcloudphone/__init__.py
aliyunsdkcloudphone/request/__init__.py
aliyunsdkcloudphone/request/v20201230/CancelTaskRequest.py
aliyunsdkcloudphone/request/v20201230/CopyImageRequest.py
aliyunsdkcloudphone/request/v20201230/CreateImageRequest.py
aliyunsdkcloudphone/request/v20201230/DeleteImagesRequest.py
aliyunsdkcloudphone/request/v20201230/DeleteInstancesRequest.py
aliyunsdkcloudphone/request/v20201230/DeleteKeyPairsRequest.py
aliyunsdkcloudphone/request/v20201230/FetchFileRequest.py
aliyunsdkcloudphone/request/v20201230/ImportImageRequest.py
aliyunsdkcloudphone/request/v20201230/ImportKeyPairRequest.py
aliyunsdkcloudphone/request/v20201230/InstallApplicationRequest.py
aliyunsdkcloudphone/request/v20201230/ListImageSharePermissionRequest.py
aliyunsdkcloudphone/request/v20201230/ListImagesRequest.py
aliyunsdkcloudphone/request/v20201230/ListInstanceTypesRequest.py
aliyunsdkcloudphone/request/v20201230/ListInstanceVncUrlRequest.py
aliyunsdkcloudphone/request/v20201230/ListInstancesRequest.py
aliyunsdkcloudphone/request/v20201230/ListKeyPairsRequest.py
aliyunsdkcloudphone/request/v20201230/ListRegionsRequest.py
aliyunsdkcloudphone/request/v20201230/ListTagKeysRequest.py
aliyunsdkcloudphone/request/v20201230/ListTagResourcesRequest.py
aliyunsdkcloudphone/request/v20201230/ListTagValuesRequest.py
aliyunsdkcloudphone/request/v20201230/ListTasksRequest.py
aliyunsdkcloudphone/request/v20201230/ListZonesRequest.py
aliyunsdkcloudphone/request/v20201230/RebootInstancesRequest.py
aliyunsdkcloudphone/request/v20201230/RenewInstancesRequest.py
aliyunsdkcloudphone/request/v20201230/ResetInstancesRequest.py
aliyunsdkcloudphone/request/v20201230/RunCommandRequest.py
aliyunsdkcloudphone/request/v20201230/RunInstancesRequest.py
aliyunsdkcloudphone/request/v20201230/SendFileRequest.py
aliyunsdkcloudphone/request/v20201230/StartInstancesRequest.py
aliyunsdkcloudphone/request/v20201230/StopInstancesRequest.py
aliyunsdkcloudphone/request/v20201230/TagResourcesRequest.py
aliyun_python_sdk_cloudphone-1.0.1.dist-info/LICENSE
aliyun_python_sdk_cloudphone-1.0.1.dist-info/METADATA
aliyun_python_sdk_cloudphone-1.0.1.dist-info/WHEEL
aliyun_python_sdk_cloudphone-1.0.1.dist-info/top_level.txt
aliyun_python_sdk_cloudphone-1.0.1.dist-info/RECORD
